testweatherinfo/__init__.py
testweatherinfo/weather.py
testweatherinfo-0.1.0.dist-info/METADATA
testweatherinfo-0.1.0.dist-info/WHEEL
testweatherinfo-0.1.0.dist-info/entry_points.txt
testweatherinfo-0.1.0.dist-info/RECORD
