Metadata-Version: 2.1
Name: testweatherinfo
Version: 0.1.0
Summary: Test publish package by poetry to PyPi
Author: bormanamadeus
Author-email: rwr79@mail.ru
Requires-Python: >=3.8.1,<4.0
Classifier: Programming Language :: Python :: 3
Classifier: Programming Language :: Python :: 3.9
Classifier: Programming Language :: Python :: 3.10
Classifier: Programming Language :: Python :: 3.11
Classifier: Programming Language :: Python :: 3.12
Classifier: Programming Language :: Python :: 3.13
Requires-Dist: colorama (>=0.4.6,<0.5.0)
Requires-Dist: fastapi (>=0.95.2,<0.96.0)
Requires-Dist: sqlalchemy (>=2.0.15,<3.0.0)
Requires-Dist: uvicorn (>=0.22.0,<0.23.0)
